setup.cfg
setup.py
demail/__init__.py
demail/backends.py
demail/models.py
demail/tests.py
demail/utils.py
django_demail.egg-info/PKG-INFO
django_demail.egg-info/SOURCES.txt
django_demail.egg-info/dependency_links.txt
django_demail.egg-info/not-zip-safe
django_demail.egg-info/requires.txt
django_demail.egg-info/top_level.txt