Metadata-Version: 1.1
Name: django-demail
Version: 0.3
Summary: Delegating email backend.
Home-page: https://github.com/goodtune/django-demail
Author: Gary Reynolds
Author-email: gary@touch.asn.au
License: UNKNOWN
Platform: UNKNOWN
Classifier: Environment :: Web Environment
Classifier: Intended Audience :: Developers
Classifier: Operating System :: OS Independent
Classifier: Programming Language :: Python
Classifier: Programming Language :: Python :: 2.7
Classifier: Topic :: Software Development :: Libraries
